[
  {
    "OutId": "3a068f7efb6bd2c4abc0a48b1f853414",
    "ParentId": "",
    "Name": "首页",
    "DisplayName": "首页",
    "IsHaveChild": false,
    "Icon": "{\"type\":\"icon-ic-sethome\"}",
    "IsIconVisible": true,
    "IsVisible": true,
    "IsInternalLink": true,
    "LinkUrl": "",
    "IsHomePage": false,
    "Sort": "1",
    "IsCustomized": false,
    "Route": "index",
    "PageOutId": "3a044e318ec39485085b19c7a7b3dcfd",
    "PageRoute": null,
    "CreateOriginType": 0,
    "OpenType": 0,
    "CreationTime": "2023-08-17 22:17:29"
  },
  {
    "OutId": "3a068f7f1249a1b853daa2ba4de7e337",
    "ParentId": "",
    "Name": "常用",
    "DisplayName": "常用",
    "IsHaveChild": false,
    "Icon": "{\"type\":\"icon-inbiz_basic-star\"}",
    "IsIconVisible": true,
    "IsVisible": true,
    "IsInternalLink": true,
    "LinkUrl": "",
    "IsHomePage": false,
    "Sort": "2",
    "IsCustomized": false,
    "Route": "1512",
    "PageOutId": "c6gvaoox3odbah8mht6i2x9of15nxy3f",
    "PageRoute": null,
    "CreateOriginType": 0,
    "OpenType": 0,
    "CreationTime": "2023-08-17 22:17:29"
  },
  {
    "OutId": "3a068f7f145d8e3aeaec0609613fcedf",
    "ParentId": "",
    "Name": "个人",
    "DisplayName": "个人",
    "IsHaveChild": false,
    "Icon": "{\"type\":\"icon-inbiz_other-user\"}",
    "IsIconVisible": true,
    "IsVisible": true,
    "IsInternalLink": true,
    "LinkUrl": "",
    "IsHomePage": false,
    "Sort": "3",
    "IsCustomized": false,
    "Route": "geren",
    "PageOutId": "l2cj0in2s8rkvjdfp9ho0o7lxi0v1v0z",
    "PageRoute": null,
    "CreateOriginType": 0,
    "OpenType": 0,
    "CreationTime": "2023-08-17 22:17:29"
  }
]