{
  "content": {
    "form": {
      "labelCol": 6,
      "wrapperCol": 18,
      "layout": "vertical",
      "labelAlign": "left",
      "model": {
        "ModelKey": "mde_cIL5cMeY",
        "ModuleId": "477386ac5fa24238a18c342afa337d2b",
        "Name": "after_sales_maintenance",
        "Describe": "维保售后",
        "ModelType": 0
      }
    },
    "schema": {
      "type": "object",
      "properties": {
        "EformInput_or1a077zs6": {
          "type": "string",
          "title": {
            "value": "产品名称",
            "status": true
          },
          "x-decorator": "FormItem",
          "x-component": "EformInput",
          "x-component-props": {
            "defaultValueType": "custom",
            "systemDefaultValue": "System_Var_LoginUserID",
            "type": "text",
            "placeholder": "EformInput.placeholder",
            "allowClear": true,
            "autoComplete": false,
            "model": {
              "Name": "m_name",
              "InnerType": "string",
              "Type": "varchar",
              "Length": 100,
              "Primary": false,
              "Unique": false,
              "IsNull": true,
              "IsGenerated": false,
              "DefaultVal": null,
              "Display": true,
              "Describe": "产品名称",
              "Scale": 0,
              "Key": "fie_8putOP3G",
              "ModelName": null,
              "TypeCN": "文本"
            },
            "modelend": {}
          },
          "x-decorator-props": {
            "style": {
              "padding": "9px 16px 9px 16px",
              "borderBottomWidth": "1px",
              "borderBottomStyle": "solid",
              "borderBottomColor": "#ddd"
            },
            "className": "EformInputContainer  wap",
            "data-designer-node-id": "sbqeyum0cuk"
          },
          "name": "EformInput_or1a077zs6",
          "x-validator": [],
          "required": true,
          "x-designable-id": "sbqeyum0cuk",
          "x-index": 0
        },
        "EformStaticList_2mvnqo84th": {
          "type": "sting",
          "title": {
            "value": "类型",
            "status": true
          },
          "x-decorator": "FormItem",
          "x-component": "EformStaticList",
          "x-component-props": {
            "selectMode": false,
            "showMode": 1,
            "placeholder": "EformStaticListView.placeholder",
            "defaultValue": [],
            "label": {
              "status": true,
              "value": "静态列表"
            },
            "autoLoading": true,
            "labelDirection": "left",
            "layoutMode": "portrait",
            "placeholder1": "点击选择",
            "selectWindowHeight": 50,
            "value": "",
            "disabledOptions": [],
            "hideDisabledOptions": false,
            "staticDataList": "b9ce5d8ad6c441479b071c66c1a9fe7e",
            "dataType": "system",
            "dataGroupId": "b9ce5d8ad6c441479b071c66c1a9fe7e",
            "model": {
              "Name": "m_type",
              "InnerType": "string",
              "Type": "varchar",
              "Length": 100,
              "Primary": false,
              "Unique": false,
              "IsNull": true,
              "IsGenerated": false,
              "DefaultVal": null,
              "Display": true,
              "Describe": "类型",
              "Scale": 0,
              "Key": "fie_83PNaB7y",
              "ModelName": null,
              "TypeCN": "文本"
            },
            "modelend": {}
          },
          "x-decorator-props": {
            "style": {
              "padding": "9px 16px 9px 16px",
              "borderBottomWidth": "1px",
              "borderBottomStyle": "solid",
              "borderBottomColor": "#ddd"
            },
            "className": "EformStaticListContainer  wap",
            "data-designer-node-id": "no57o7t9xvw"
          },
          "name": "EformStaticList_2mvnqo84th",
          "required": true,
          "x-designable-id": "no57o7t9xvw",
          "x-index": 1
        },
        "EformMemberSelect_fbabbi22tt": {
          "title": {
            "value": "申请人",
            "status": true
          },
          "type": "Array",
          "x-decorator": "FormItem",
          "x-component": "EformMemberSelect",
          "x-component-props": {
            "label": {
              "status": true,
              "value": "EformMemberSelect.title"
            },
            "placeholder": "EformMemberSelect.lang.plzSelect",
            "multiple": false,
            "tabs": [
              "user"
            ],
            "readonly": false,
            "visible": false,
            "className": "",
            "model": {
              "Name": "m_people",
              "InnerType": "string",
              "Type": "varchar",
              "Length": 100,
              "Primary": false,
              "Unique": false,
              "IsNull": true,
              "IsGenerated": false,
              "DefaultVal": null,
              "Display": true,
              "Describe": "申请人",
              "Scale": 0,
              "Key": "fie_wkaacvWA",
              "ModelName": null,
              "TypeCN": "文本"
            },
            "modelend": {}
          },
          "x-decorator-props": {
            "style": {
              "padding": "9px 16px 9px 16px",
              "borderBottomWidth": "1px",
              "borderBottomStyle": "solid",
              "borderBottomColor": "#ddd"
            },
            "className": "EformMemberSelectContainer  wap",
            "data-designer-node-id": "n2s7p0usyfs"
          },
          "name": "EformMemberSelect_fbabbi22tt",
          "required": true,
          "x-designable-id": "n2s7p0usyfs",
          "x-index": 2
        },
        "EformDatePicker_3le2h3hlp5": {
          "type": "string",
          "title": {
            "value": "申请时间",
            "status": true
          },
          "x-decorator": "FormItem",
          "x-component": "EformDatePicker",
          "x-component-props": {
            "format": "YYYY-MM-DD",
            "defaultValueType": "variableDefaultValue",
            "customDefaultValue": null,
            "variableDefaultValue": "nowTime",
            "placeholder": "EformDatePicker.placeholder",
            "allowBeforeNow": true,
            "allowClear": true,
            "min": "",
            "max": "",
            "model": {
              "Name": "m_time",
              "InnerType": "datetime",
              "Type": "datetime",
              "Length": 0,
              "Primary": false,
              "Unique": false,
              "IsNull": true,
              "IsGenerated": false,
              "DefaultVal": null,
              "Display": true,
              "Describe": "申请时间",
              "Scale": 0,
              "Key": "fie_SjVi9HGw",
              "ModelName": null,
              "TypeCN": "时间"
            },
            "modelend": {}
          },
          "x-decorator-props": {
            "style": {
              "padding": "9px 16px 9px 16px",
              "borderBottomWidth": "1px",
              "borderBottomStyle": "solid",
              "borderBottomColor": "#ddd"
            },
            "className": "EformDatePickerContainer  wap",
            "data-designer-node-id": "8udnptv2klt"
          },
          "name": "EformDatePicker_3le2h3hlp5",
          "required": true,
          "x-designable-id": "8udnptv2klt",
          "x-index": 3
        },
        "EformTextArea_bl6n7ll5o2": {
          "type": "string",
          "title": {
            "value": "备注",
            "status": true
          },
          "x-decorator": "FormItem",
          "x-component": "EformTextArea",
          "x-component-props": {
            "defaultValue": "",
            "placeholder": "EformTextArea.placeholder",
            "showCount": false,
            "model": {
              "Name": "m_notes",
              "InnerType": "string",
              "Type": "text",
              "Length": 0,
              "Primary": false,
              "Unique": false,
              "IsNull": true,
              "IsGenerated": false,
              "DefaultVal": null,
              "Display": true,
              "Describe": "备注",
              "Scale": 0,
              "Key": "fie_KfPdOE4s",
              "ModelName": null,
              "TypeCN": "长文本"
            },
            "modelend": {}
          },
          "x-decorator-props": {
            "style": {
              "padding": "9px 16px 9px 16px",
              "borderBottomWidth": "1px",
              "borderBottomStyle": "solid",
              "borderBottomColor": "#ddd"
            },
            "className": "EformTextAreaContainer  wap",
            "data-designer-node-id": "94d3rzh3b4f"
          },
          "name": "EformTextArea_bl6n7ll5o2",
          "x-designable-id": "94d3rzh3b4f",
          "x-index": 4
        },
        "ImgUpload_yrec37jdfb": {
          "type": "array",
          "title": {
            "value": "上传图片",
            "status": true
          },
          "x-decorator": "FormItemVertical",
          "x-component": "ImgUpload",
          "x-component-props": {
            "imgSize": "1MB",
            "multiple": true,
            "required": false,
            "imgType": [
              "jpg",
              "png",
              "bmp",
              "jpeg",
              "gif",
              "svg+xml"
            ],
            "imgHeight": "",
            "imgWidth": "",
            "cutting": false,
            "subFolder": false,
            "repeatStrategy": "majorUpgrade",
            "storageMode": "modalType",
            "thumbnail": false,
            "placeHolder": "ImgUploadView.placeHolder",
            "fixedHeight": false,
            "createChildrenFolder": {},
            "model": {
              "Name": "m_pic",
              "InnerType": "string",
              "Type": "text",
              "Length": 0,
              "Primary": false,
              "Unique": false,
              "IsNull": true,
              "IsGenerated": false,
              "DefaultVal": null,
              "Display": true,
              "Describe": "上传图片",
              "Scale": 0,
              "Key": "fie_JrrtTGI7",
              "ModelName": null,
              "TypeCN": "长文本"
            },
            "modelend": {}
          },
          "x-component-biz-props": {
            "toFolderType": "enterpriseLib",
            "toFolder": [
              {
                "folderid": 101,
                "areaid": -1,
                "parentfolderid": 1,
                "foldercode": "",
                "foldersortorder": -1,
                "foldername": "03内部测试",
                "folderpath": "1\\101",
                "foldersize": 12904296739,
                "foldermaxfoldersize": 0,
                "folderalertsize": 0,
                "foldermaxfilesize": 0,
                "folderforbiddenfileextensions": "",
                "folderchildfolderscount": 1671,
                "folderchildfilescount": 2206,
                "securitylevelid": 0,
                "folderstate": 0,
                "folderlockcount": -1,
                "foldercreatetime": "2022-06-06 15:09:43",
                "foldercreateoperator": 2,
                "foldercreateoperatorname": "Administrator",
                "foldermodifytime": "2023-04-17 17:14:55",
                "foldermodifyoperator": 1115,
                "foldermodifyoperatorname": "张国辉",
                "folderarchivetime": "0001-01-01 08:05:00",
                "folderarchiveoperator": -1,
                "foldercurverid": -1,
                "foldernewestverid": -1,
                "foldertype": 1,
                "folderguid": "07476a61-0190-46e6-9056-06c60ce3733a",
                "folderownerid": 2,
                "folderofflinepermission": 1,
                "isdeleted": false,
                "folderdeletetime": "0001-01-01 08:05:00",
                "folderdeleteoperator": -1,
                "folderdeleteoperatorname": null,
                "folderiscascadedelete": false,
                "folderpurge": -1,
                "folderpurgetime": "0001-01-01 08:05:00",
                "folderpurgeoperator": -1,
                "folderpurgeoperatorname": null,
                "folderverstrategy": -1,
                "foldercreatetype": -1,
                "folderdefaultviewid": -1,
                "folderpermstrategy": -1,
                "instanceid": 1,
                "name": "03内部测试",
                "relativepath": "企业库\\03内部测试",
                "teamicon": null,
                "children": null,
                "childrenpagesize": 0,
                "childrentotalcount": 0,
                "toptargetfoldername": null,
                "key": 101,
                "address": "企业库/03内部测试",
                "id": 101
              }
            ]
          },
          "x-decorator-props": {
            "style": {
              "padding": "9px 16px 9px 16px",
              "borderBottomWidth": "1px",
              "borderBottomStyle": "solid",
              "borderBottomColor": "#ddd"
            },
            "className": "ImgUploadContainer  wap",
            "data-designer-node-id": "me7e8iywrtu",
            "colon": false
          },
          "name": "ImgUpload_yrec37jdfb",
          "x-designable-id": "me7e8iywrtu",
          "x-index": 5
        },
        "ProcessButton_0ocx1gcpcq": {
          "type": "void",
          "x-decorator": "Container",
          "x-decorator-props": {
            "clickable": true,
            "className": "ProcessButtonContainer  wap",
            "data-designer-node-id": "09pv6jma8wa"
          },
          "x-component": "ProcessButton",
          "x-component-props": {
            "tips": "",
            "buttonVisible": "visible",
            "webbuttonConfig": [
              {
                "action": "initiate",
                "name": "processButton.initiate",
                "type": "initiate",
                "bgColor": "#1989fa",
                "id": "",
                "taskType": "faqishenqing"
              },
              {
                "action": "approve",
                "name": "processButton.approve",
                "type": "approve",
                "bgColor": "#1989fa",
                "id": "",
                "taskType": "faqishenqing"
              },
              {
                "action": "returnsBack",
                "name": "processButton.returnsBack",
                "type": "returnsBack",
                "bgColor": "#1989fa",
                "id": "",
                "taskType": "faqishenqing"
              },
              {
                "action": "cancel",
                "name": "processButton.cancel",
                "type": "cancel",
                "bgColor": "#1989fa",
                "id": "",
                "taskType": "faqishenqing"
              }
            ],
            "wapbuttonConfig": [
              {
                "action": "initiate",
                "name": "processbutton.initiate",
                "type": "initiate",
                "bgColor": "#1989fa",
                "id": "",
                "taskType": "faqishenqing"
              },
              {
                "action": "approve",
                "name": "processButton.approve",
                "type": "approve",
                "bgColor": "#1989fa",
                "id": "",
                "taskType": "faqishenqing"
              },
              {
                "action": "returnsBack",
                "name": "processButton.returnPrestep",
                "type": "returnsBack",
                "bgColor": "#1989fa",
                "id": "",
                "taskType": "faqishenqing"
              },
              {
                "action": "cancel",
                "name": "processButton.cancel",
                "type": "cancel",
                "bgColor": "#1989fa",
                "id": "",
                "taskType": "faqishenqing"
              }
            ],
            "radius": 4,
            "showCCmember": true,
            "showComment": true
          },
          "name": "ProcessButton_0ocx1gcpcq",
          "x-designable-id": "09pv6jma8wa",
          "x-index": 6
        },
        "ProcessLogBtn_lcai72dp36": {
          "type": "void",
          "x-decorator": "Container",
          "x-decorator-props": {
            "clickable": true,
            "className": "ProcessLogBtnContainer  wap",
            "data-designer-node-id": "fw0hqh8ivv6"
          },
          "x-component": "ProcessLogBtn",
          "x-component-props": {
            "minWidth": 100,
            "maxWidth": "",
            "text": "button",
            "type": "primary"
          },
          "name": "ProcessLogBtn_lcai72dp36",
          "x-designable-id": "fw0hqh8ivv6",
          "x-index": 7
        }
      },
      "x-designable-id": "b21wrzop0dt"
    }
  }
}